src/__init__.py
src/modeling/__init__.py
src/modeling/trustii.py
trustii_ml-0.0.5.dist-info/LICENSE
trustii_ml-0.0.5.dist-info/METADATA
trustii_ml-0.0.5.dist-info/WHEEL
trustii_ml-0.0.5.dist-info/top_level.txt
trustii_ml-0.0.5.dist-info/RECORD
