Metadata-Version: 2.1
Name: trustii-ml
Version: 0.0.5
Summary: To add Trustii Class to Python Path
Home-page: UNKNOWN
Author: tiwars
Author-email: mockinbird24@gmail.com
License: UNKNOWN
Platform: UNKNOWN
Classifier: Programming Language :: Python :: 3
Classifier: Operating System :: OS Independent
Requires-Python: >=3.6
